LICENSE
README.md
setup.py
dac/__init__.py
dac/__main__.py
dac/compare/__init__.py
dac/compare/encodec.py
dac/model/__init__.py
dac/model/base.py
dac/model/dac.py
dac/model/discriminator.py
dac/nn/__init__.py
dac/nn/layers.py
dac/nn/loss.py
dac/nn/quantize.py
dac/utils/__init__.py
dac/utils/decode.py
dac/utils/encode.py
descript_audio_codec_unofficial.egg-info/PKG-INFO
descript_audio_codec_unofficial.egg-info/SOURCES.txt
descript_audio_codec_unofficial.egg-info/dependency_links.txt
descript_audio_codec_unofficial.egg-info/requires.txt
descript_audio_codec_unofficial.egg-info/top_level.txt
tests/__init__.py
tests/test_cli.py
tests/test_train.py