Metadata-Version: 2.1
Name: descript-audio-codec-unofficial
Version: 1.0.0
Summary: A high-quality general neural audio codec.
Home-page: https://github.com/descriptinc/descript-audio-codec
Author: Prem Seetharaman, Rithesh Kumar
Author-email: prem@descript.com
License: MIT
Keywords: audio,compression,machine learning
Classifier: Intended Audience :: Developers
Classifier: Natural Language :: English
Classifier: Programming Language :: Python :: 3.7
Classifier: Topic :: Artistic Software
Classifier: Topic :: Multimedia
Classifier: Topic :: Multimedia :: Sound/Audio
Classifier: Topic :: Multimedia :: Sound/Audio :: Editors
Classifier: Topic :: Software Development :: Libraries
License-File: LICENSE
Requires-Dist: argbind>=0.3.7
Requires-Dist: descript-audiotools-unofficial
Requires-Dist: einops
Requires-Dist: numpy
Requires-Dist: torch
Requires-Dist: torchaudio
Requires-Dist: tqdm
Provides-Extra: dev
Requires-Dist: pytest; extra == "dev"
Requires-Dist: pytest-cov; extra == "dev"
Requires-Dist: pynvml; extra == "dev"
Requires-Dist: psutil; extra == "dev"
Requires-Dist: pandas; extra == "dev"
Requires-Dist: onnx; extra == "dev"
Requires-Dist: onnx-simplifier; extra == "dev"
Requires-Dist: seaborn; extra == "dev"
Requires-Dist: jupyterlab; extra == "dev"
Requires-Dist: pandas; extra == "dev"
Requires-Dist: watchdog; extra == "dev"
Requires-Dist: pesq; extra == "dev"
Requires-Dist: tabulate; extra == "dev"
Requires-Dist: encodec; extra == "dev"
